botwinick_sci/__init__.py
botwinick_sci/chem.py
botwinick_sci/safety.py
botwinick_sci-0.0.1.dist-info/LICENSE
botwinick_sci-0.0.1.dist-info/METADATA
botwinick_sci-0.0.1.dist-info/WHEEL
botwinick_sci-0.0.1.dist-info/top_level.txt
botwinick_sci-0.0.1.dist-info/RECORD
