Metadata-Version: 2.1
Name: botwinick-sci
Version: 0.0.1
Summary: Utility functions for scientific/chemical/safety applications
Home-page: https://github.com/dbotwinick/python-botwinick-sci
Author: Drew Botwinick
Author-email: foss@drewbotwinick.com
License: UNKNOWN
Platform: UNKNOWN
Classifier: Development Status :: 3 - Alpha
Classifier: Intended Audience :: Developers
Classifier: Programming Language :: Python :: 2
Classifier: Programming Language :: Python :: 3
Classifier: License :: OSI Approved :: BSD License
Classifier: Operating System :: OS Independent
Requires-Python: >=2.7, >=3.6
Requires-Dist: vpd
Requires-Dist: numpy
Requires-Dist: scipy
